git_quilt/__init__.py
git_quilt/continuations.py
git_quilt/git.py
git_quilt/git_swap.py
git_quilt/py.typed
git_quilt-0.0.2.dist-info/METADATA
git_quilt-0.0.2.dist-info/WHEEL
git_quilt-0.0.2.dist-info/entry_points.txt
git_quilt-0.0.2.dist-info/RECORD
