Metadata-Version: 2.4
Name: git-quilt
Version: 0.0.2
Summary: git based patch manager
License: Apache-2.0
Author: Lawrence D'Anna
Author-email: larry@elder-gods.org
Requires-Python: >=3.12
Classifier: License :: OSI Approved :: Apache Software License
Classifier: Programming Language :: Python :: 3
Classifier: Programming Language :: Python :: 3.12
Classifier: Programming Language :: Python :: 3.13
Classifier: Programming Language :: Python :: 3.14
